scripts/__init__.py
scripts/fragmentstein.py
scripts/fragmentstein.sh
fragmentstein-2023.4.dist-info/LICENSE
fragmentstein-2023.4.dist-info/METADATA
fragmentstein-2023.4.dist-info/WHEEL
fragmentstein-2023.4.dist-info/entry_points.txt
fragmentstein-2023.4.dist-info/RECORD
